{
	"configurations" : 
	[
		{
			"directories" : 
			[
				{
					"build" : ".",
					"jsonFile" : "directory-.-Debug-d0094a50bb2071803777.json",
					"minimumCMakeVersion" : 
					{
						"string" : "3.24"
					},
					"projectIndex" : 0,
					"source" : ".",
					"targetIndexes" : 
					[
						0
					]
				}
			],
			"name" : "Debug",
			"projects" : 
			[
				{
					"directoryIndexes" : 
					[
						0
					],
					"name" : "fractal_explorer",
					"targetIndexes" : 
					[
						0
					]
				}
			],
			"targets" : 
			[
				{
					"directoryIndex" : 0,
					"id" : "fractal_explorer::@6890427a1f51a3e7e1df",
					"jsonFile" : "target-fractal_explorer-Debug-319bcea7a5681c672d78.json",
					"name" : "fractal_explorer",
					"projectIndex" : 0
				}
			]
		}
	],
	"kind" : "codemodel",
	"paths" : 
	{
		"build" : "C:/Users/Peter Kang/source/repos/fractal-explorer/cmake-build-debug",
		"source" : "C:/Users/Peter Kang/source/repos/fractal-explorer"
	},
	"version" : 
	{
		"major" : 2,
		"minor" : 4
	}
}
